{"assets":[{"id":"comp_0","layers":[{"ddd":0,"ind":0,"ty":4,"nm":"beijing 2","ks":{"o":{"k":[{"i":{"x":[0.667],"y":[1]},"o":{"x":[0.333],"y":[0]},"n":["0p667_1_0p333_0"],"t":0,"s":[21],"e":[0]},{"t":50}]},"r":{"k":0},"p":{"k":[150,150,0]},"a":{"k":[12.319,-24.181,0]},"s":{"k":[{"i":{"x":[0.667,0.667,0.667],"y":[1,1,0.667]},"o":{"x":[0.333,0.333,0.333],"y":[0,0,0.333]},"n":["0p667_1_0p333_0","0p667_1_0p333_0","0p667_0p667_0p333_0p333"],"t":0,"s":[100,100,100],"e":[230,230,100]},{"t":50}]}},"ao":0,"shapes":[{"ty":"gr","it":[{"d":1,"ty":"el","s":{"k":[120,120]},"p":{"k":[0,0]},"nm":"椭圆路径 1","mn":"ADBE Vector Shape - Ellipse"},{"ty":"fl","fillEnabled":true,"c":{"k":[0.13,0.47,0.8,1]},"o":{"k":100},"nm":"填充 1","mn":"ADBE Vector Graphic - Fill"},{"ty":"tr","p":{"k":[12.319,-24.181],"ix":2},"a":{"k":[0,0],"ix":1},"s":{"k":[100,100],"ix":3},"r":{"k":0,"ix":6},"o":{"k":100,"ix":7},"sk":{"k":0,"ix":4},"sa":{"k":0,"ix":5},"nm":"变换"}],"nm":"椭圆 1","np":3,"mn":"ADBE Vector Group"},{"ty":"st","fillEnabled":true,"c":{"k":[0.56,0.9,1,1]},"o":{"k":100},"w":{"k":2},"lc":1,"lj":1,"ml":4,"nm":"描边 1","mn":"ADBE Vector Graphic - Stroke"}],"ip":0,"op":75,"st":0,"bm":0,"sr":1},{"ddd":0,"ind":1,"ty":4,"nm":"beijing 3","ks":{"o":{"k":[{"i":{"x":[0.667],"y":[1]},"o":{"x":[0.333],"y":[0]},"n":["0p667_1_0p333_0"],"t":25,"s":[21],"e":[0]},{"t":75}]},"r":{"k":0},"p":{"k":[150,150,0]},"a":{"k":[12.319,-24.181,0]},"s":{"k":[{"i":{"x":[0.405,0.405,0.667],"y":[1,1,0.667]},"o":{"x":[0.333,0.333,0.333],"y":[0,0,0.333]},"n":["0p405_1_0p333_0","0p405_1_0p333_0","0p667_0p667_0p333_0p333"],"t":25,"s":[100,100,100],"e":[230,230,100]},{"t":75}]}},"ao":0,"shapes":[{"ty":"gr","it":[{"d":1,"ty":"el","s":{"k":[120,120]},"p":{"k":[0,0]},"nm":"椭圆路径 1","mn":"ADBE Vector Shape - Ellipse"},{"ty":"fl","fillEnabled":true,"c":{"k":[0.13,0.47,0.8,1]},"o":{"k":100},"nm":"填充 1","mn":"ADBE Vector Graphic - Fill"},{"ty":"tr","p":{"k":[12.319,-24.181],"ix":2},"a":{"k":[0,0],"ix":1},"s":{"k":[100,100],"ix":3},"r":{"k":0,"ix":6},"o":{"k":100,"ix":7},"sk":{"k":0,"ix":4},"sa":{"k":0,"ix":5},"nm":"变换"}],"nm":"椭圆 1","np":3,"mn":"ADBE Vector Group"},{"ty":"st","fillEnabled":true,"c":{"k":[0.56,0.9,1,1]},"o":{"k":100},"w":{"k":2},"lc":1,"lj":1,"ml":4,"nm":"描边 1","mn":"ADBE Vector Graphic - Stroke"}],"ip":0,"op":75,"st":0,"bm":0,"sr":1}]}],"layers":[{"ddd":0,"ind":0,"ty":4,"nm":"形状图层 1","td":1,"ks":{"o":{"k":100},"r":{"k":0},"p":{"k":[152.294,149.704,0]},"a":{"k":[0,0,0]},"s":{"k":[100,100,100]}},"ao":0,"shapes":[{"ty":"gr","it":[{"ind":0,"ty":"sh","ks":{"k":{"i":[[-33.137,0],[0,-33.137],[33.137,0],[0,33.137]],"o":[[33.137,0],[0,33.137],[-33.137,0],[0,-33.137]],"v":[[0,-60],[60,0],[0,60],[-60,0]],"c":true}},"nm":"路径 1","mn":"ADBE Vector Shape - Group"},{"ty":"fl","fillEnabled":true,"c":{"k":[0.13,0.47,0.8,1]},"o":{"k":100},"nm":"填充 1","mn":"ADBE Vector Graphic - Fill"},{"ty":"tr","p":{"k":[-2.294,0.296],"ix":2},"a":{"k":[0,0],"ix":1},"s":{"k":[100,100],"ix":3},"r":{"k":0,"ix":6},"o":{"k":100,"ix":7},"sk":{"k":0,"ix":4},"sa":{"k":0,"ix":5},"nm":"变换"}],"nm":"椭圆 1","np":3,"mn":"ADBE Vector Group"}],"ip":0,"op":75,"st":0,"bm":0,"sr":1},{"ddd":0,"ind":1,"ty":0,"nm":"预合成 1","tt":2,"refId":"comp_0","ks":{"o":{"k":100},"r":{"k":0},"p":{"k":[150,150,0]},"a":{"k":[150,150,0]},"s":{"k":[100,100,100]}},"ao":0,"w":300,"h":300,"ip":0,"op":75,"st":0,"bm":0,"sr":1}],"v":"4.5.3","ddd":0,"ip":0,"op":75,"fr":25,"w":300,"h":300}